dict_traverser/__init__.py
dict_traverser/dict_traverser.py
dict_traverser-1.0.1.dist-info/licenses/LICENSE
dict_traverser-1.0.1.dist-info/METADATA
dict_traverser-1.0.1.dist-info/WHEEL
dict_traverser-1.0.1.dist-info/top_level.txt
dict_traverser-1.0.1.dist-info/RECORD
