Metadata-Version: 2.4
Name: dict-traverser
Version: 1.0.1
Summary: Dict wrapper for accessing, updating, and deleting values in deeply nested dictionaries and lists using dot-notation paths with optional array indexing.
Author-email: Carlos Venencia <carlos@cvenencia.com>
License: MIT
Requires-Python: >=3.10
License-File: LICENSE
Provides-Extra: test
Requires-Dist: pytest; extra == "test"
Dynamic: license-file
